md_toc/__init__.py
md_toc/__main__.py
md_toc/api.py
md_toc/cli.py
md_toc/constants.py
md_toc/exceptions.py
md_toc/generic.py
md_toc/types.py
md_toc/cmark/__init__.py
md_toc/cmark/buffer_c.py
md_toc/cmark/buffer_h.py
md_toc/cmark/chunk_h.py
md_toc/cmark/cmark_ctype_c.py
md_toc/cmark/cmark_h.py
md_toc/cmark/houdini_h.py
md_toc/cmark/houdini_html_u_c.py
md_toc/cmark/inlines_c.py
md_toc/cmark/node_c.py
md_toc/cmark/node_h.py
md_toc/cmark/references_c.py
md_toc/cmark/references_h.py
md_toc/cmark/scanners_c.py
md_toc/cmark/scanners_h.py
md_toc/cmark/utf8_c.py
md_toc-9.0.0.dist-info/LICENSE.txt
md_toc-9.0.0.dist-info/METADATA
md_toc-9.0.0.dist-info/WHEEL
md_toc-9.0.0.dist-info/entry_points.txt
md_toc-9.0.0.dist-info/top_level.txt
md_toc-9.0.0.dist-info/RECORD
