Metadata-Version: 2.1
Name: md_toc
Version: 9.0.0
Summary: Automatically generate and add an accurate table of contents to markdown files
Home-page: https://blog.franco.net.eu.org/software/#md-toc
Author: Franco Masotti
Author-email: franco.masotti@tutanota.com
License: GPLv3+,
Project-URL: Bug Tracker, https://github.com/frnmst/md-toc/issues
Project-URL: Documentation, https://docs.franco.net.eu.org/md-toc/
Project-URL: API Reference, https://docs.franco.net.eu.org/md-toc/api.html
Project-URL: Source Code, https://github.com/frnmst/md-toc
Project-URL: Changelog, https://blog.franco.net.eu.org/software/CHANGELOG-md-toc.html
Project-URL: Funding, https://github.com/frnmst/md-toc#support-this-project
Keywords: markdown,toc,text,table-of-contents,documentation
Classifier: Development Status :: 5 - Production/Stable
Classifier: Topic :: Documentation
Classifier: Topic :: Software Development
Classifier: Topic :: Text Processing
Classifier: Topic :: Text Processing :: Markup :: Markdown
Classifier: Topic :: Utilities
Classifier: Intended Audience :: Developers
Classifier: Intended Audience :: End Users/Desktop
Classifier: Intended Audience :: Information Technology
Classifier: Environment :: Console
Classifier: License :: OSI Approved :: GNU General Public License v3 or later (GPLv3+)
Classifier: Programming Language :: Python :: 3
Classifier: Programming Language :: Python :: 3.8
Classifier: Programming Language :: Python :: 3.9
Classifier: Programming Language :: Python :: 3.10
Classifier: Programming Language :: Python :: 3.11
Classifier: Programming Language :: Python :: 3.12
Classifier: Programming Language :: Python :: 3.13
Requires-Python: >=3.8
License-File: LICENSE.txt
Requires-Dist: fpyutils<5,>=4.0.1
